shannonca/__init__.py
shannonca/connectors.py
shannonca/correctors.py
shannonca/dimred.py
shannonca/embedders.py
shannonca/generate.py
shannonca/integrate.py
shannonca/lknn.py
shannonca/optimize.py
shannonca/plotting.py
shannonca/score.py
shannonca/scorers.py
shannonca/utils.py
shannonca-0.0.9.dist-info/LICENSE
shannonca-0.0.9.dist-info/METADATA
shannonca-0.0.9.dist-info/WHEEL
shannonca-0.0.9.dist-info/top_level.txt
shannonca-0.0.9.dist-info/RECORD
