Metadata-Version: 2.1
Name: shannonca
Version: 0.0.9
Summary: Informative Dimensionality Reduction via Shannon Component Analysis
Home-page: https://github.com/bdemeo/shannonca
Download-URL: https://github.com/bendemeo/shannonca/archive/refs/tags/0.0.1.tar.gz
Author: Benjamin DeMeo
Author-email: bdemeo@g.harvard.edu
License: MIT
Keywords: Shannon,Information,Dimensionality,reduction,single-cell,RNA
License-File: LICENSE
Requires-Dist: scikit-learn
Requires-Dist: scipy
Requires-Dist: numpy
Requires-Dist: pandas
Requires-Dist: scanpy
